cgstep/__init__.py
cgstep/cli.py
cgstep/tmc5240.py
cgstep-1.6.dist-info/licenses/LICENSE
cgstep-1.6.dist-info/METADATA
cgstep-1.6.dist-info/WHEEL
cgstep-1.6.dist-info/entry_points.txt
cgstep-1.6.dist-info/top_level.txt
cgstep-1.6.dist-info/RECORD
