Metadata-Version: 2.4
Name: cgstep
Version: 1.6
Summary: Python package and command line tool to control stepping motor driver RPZ-Stepper/TMC5240 on Raspberry Pi
Home-page: https://github.com/IndoorCorgi/cgstep
Author: Indoor Corgi
Author-email: indoorcorgi@gmail.com
License: Apache License 2.0
Requires-Python: >=3.9
License-File: LICENSE
Dynamic: author
Dynamic: author-email
Dynamic: home-page
Dynamic: license
Dynamic: license-file
Dynamic: requires-python
Dynamic: summary
